fioo/__init__.py
fioo/fioo.py
fioo-0.4.1.dist-info/METADATA
fioo-0.4.1.dist-info/WHEEL
fioo-0.4.1.dist-info/top_level.txt
fioo-0.4.1.dist-info/RECORD
