Metadata-Version: 2.1
Name: fioo
Version: 0.4.1
Summary: file and folder operation utility packages
Home-page: https://github.com/ZDragon1996/FIOO
Author: Jialong Zhang
Author-email: BubbleEcho@protonmail.com
License: UNKNOWN
Platform: UNKNOWN
Classifier: Programming Language :: Python :: 3
Classifier: License :: OSI Approved :: MIT License
Classifier: Operating System :: OS Independent
